{
	"$schema": "https://schemas.wp.org/trunk/block.json",
	"apiVersion": 2,
	"name": "amem/form",
	"title": "Adv. Members Form",
	"category": "text",
	"description": "Add Advanced Members Form to your content.",
	"textdomain": "advanced-members",
	"attributes": {
		"type": {
			"enum": [ "", "form", "preForm" ],
			"default": "form"
		},
		"form": {
			"type": "number",
			"default": 0
		},
		"preForm": {
			"type": "string",
			"default": ""
		},
		"hash": {
			"type": "string",
			"default": ""
		},
		"title": {
			"type": "string",
  			"default": ""
		}
	},
	"usesContext": [ "form", "type", "hasy" ],
	"supports": {
		"className": true,
		"customClassName": true,
		"anchor": true,
		"html": true
	},
	"_supports": {
		"align": [ "wide", "full" ],
		"anchor": false,
		"className": false,
		"color": {
			"gradients": true,
			"link": true,
			"__experimentalDefaultControls": {
				"background": true,
				"text": true
			}
		},
		"spacing": {
			"margin": true,
			"padding": true,
			"__experimentalDefaultControls": {
				"margin": false,
				"padding": false
			}
		},
		"typography": {
			"fontSize": true,
			"lineHeight": true,
			"__experimentalFontFamily": true,
			"__experimentalFontStyle": true,
			"__experimentalFontWeight": true,
			"__experimentalLetterSpacing": true,
			"__experimentalTextTransform": true,
			"__experimentalTextDecoration": true,
			"__experimentalWritingMode": true,
			"__experimentalDefaultControls": {
				"fontSize": true
			}
		},
		"__unstablePasteTextInline": true,
		"__experimentalSlashInserter": true,
		"interactivity": {
			"clientNavigation": true
		}
	},
	"style": "wp-block-amem-form"
}
